setup.cfg
setup.py
python_xmlstats.egg-info/PKG-INFO
python_xmlstats.egg-info/SOURCES.txt
python_xmlstats.egg-info/dependency_links.txt
python_xmlstats.egg-info/top_level.txt
xmlstats/__init__.py