Metadata-Version: 1.1
Name: python-xmlstats
Version: 1.0.0
Summary: Client for https://erikberg.com/api
Home-page: https://github.com/Krokop/python-xmlstats
Author: Serbokryl Oleg
Author-email: chezar1995@gmail.com
License: UNKNOWN
Download-URL: https://github.com/Krokop/python-xmlstats/tarball/0.14
Keywords: NBA stas api,xmlstats,NBA API,nba api stats
Platform: UNKNOWN
